{"game_name": "实战右下角标准化定式（3手）", "black": "黑棋", "white": "白棋", "black_rank": "", "white_rank": "", "board_size": 19, "handicap": 0, "handicap_stones": [], "result": "", "tree": {"color": null, "coord": null, "properties": {"C": "实战右下角标准化定式（3手）"}, "children": [{"color": "B", "coord": "pc", "children": [{"color": "W", "coord": "nc", "children": [{"color": "B", "coord": "pe", "children": [{"color": "W", "coord": "qd", "children": [{"color": "B", "coord": "qc", "children": [{"color": "W", "coord": "me"}]}]}, {"color": "W", "coord": "kc", "properties": {"C": "出现次数:180"}}, {"color": "W", "coord": "qf", "properties": {"C": "出现次数:124"}, "children": [{"color": "B", "coord": "qe", "properties": {"C": "出现次数:71"}}]}, {"color": "W", "coord": "tt", "properties": {"C": "出现次数:86"}}, {"color": "W", "coord": "ne", "properties": {"C": "出现次数:69"}}]}]}]}]}, "download_filename": "joseki_061.sgf", "default_move": 3, "max_moves": 6}